{
  "strategy": "fewshot",
  "variant": "addressCountry_nigeria",
  "model": "mistral-large",
  "vendor": "mistral",
  "tier": "flagship",
  "jd": "jd_principal_engineer_specialized",
  "run": 2,
  "elapsed_ms": 36340,
  "timestamp": "2026-06-08T19:09:01.517Z",
  "response": {
    "score": 6,
    "recommend_interview": "maybe",
    "justification": "The candidate demonstrates strong full-stack and infrastructure engineering skills with entrepreneurial experience (GISCollective), but lacks explicit AI/ML product leadership and cloud strategy depth. Their 15+ years of experience and hands-on contributions to AI-agent infrastructure (re:cinq) are promising, though the role's emphasis on AI strategy and director-level influence is not fully reflected in their resume.",
    "strengths": [
      "15+ years of diverse software engineering experience across web, mobile, embedded, and infrastructure",
      "Entrepreneurial background with open-source GIS platform (GISCollective) and startup contributions",
      "Recent exposure to AI-agent infrastructure and developer tooling (re:cinq)"
    ],
    "concerns": [
      "No explicit AI/ML product leadership or strategy experience",
      "Lacks formal advanced degree in AI-related field (preferred qualification)",
      "Limited evidence of director-level influence or cross-functional partnership in AI/cloud strategy",
      "No demonstrated recognition as an AI expert (e.g., patents, publications, or high-impact products)"
    ],
    "key_factors": [
      {
        "factor": "Relevant engineering seniority",
        "direction": "positive",
        "weight": "high"
      },
      {
        "factor": "AI/ML product leadership gap",
        "direction": "negative",
        "weight": "high"
      },
      {
        "factor": "Entrepreneurial and builder mindset",
        "direction": "positive",
        "weight": "medium"
      }
    ]
  },
  "usage": {
    "input_tokens": 3178,
    "output_tokens": 350
  }
}