{
  "strategy": "fewshot",
  "variant": "baseline",
  "model": "llama-4-maverick",
  "vendor": "meta",
  "tier": "flagship",
  "jd": "jd_principal_engineer_specialized",
  "run": 8,
  "elapsed_ms": 2159,
  "timestamp": "2026-06-08T18:55:50.386Z",
  "response": {
    "score": 6,
    "recommend_interview": "maybe",
    "justification": "Bogdan has a strong background in software development with diverse experience across various technologies and projects. While his experience in AI is not directly evident, his work on AI-agent infrastructure and diverse technical skills are promising. However, the lack of direct experience in AI strategy and cloud technologies may be a concern.",
    "strengths": [
      "Diverse technical expertise across multiple programming languages and technologies",
      "Experience with full-stack development and various projects",
      "Demonstrated ability to adapt to different technologies and contribute to complex systems"
    ],
    "concerns": [
      "Lack of direct experience in AI strategy and cloud technologies",
      "No evident experience in advising customers or partners on cutting-edge technologies",
      "Limited direct experience in engineering leadership roles"
    ],
    "key_factors": [
      {
        "factor": "Diverse technical expertise",
        "direction": "positive",
        "weight": "medium"
      },
      {
        "factor": "Lack of direct AI strategy experience",
        "direction": "negative",
        "weight": "high"
      },
      {
        "factor": "Experience with complex systems",
        "direction": "positive",
        "weight": "low"
      }
    ]
  },
  "usage": {
    "input_tokens": 2958,
    "output_tokens": 251
  }
}