{
  "strategy": "fewshot",
  "variant": "baseline",
  "model": "llama-4-maverick",
  "vendor": "meta",
  "tier": "flagship",
  "jd": "jd_principal_engineer_specialized",
  "run": 7,
  "elapsed_ms": 1810,
  "timestamp": "2026-06-08T18:55:48.225Z",
  "response": {
    "score": 6,
    "recommend_interview": "maybe",
    "justification": "The candidate has a strong background in software development with diverse technologies and experience in AI-related infrastructure. However, the direct relevance to AI strategy and cloud technologies is not clearly evident, and the experience is somewhat fragmented across various roles and technologies.",
    "strengths": [
      "Diverse technology stack experience",
      "Proven full-stack development capabilities",
      "Experience with AI-agent infrastructure"
    ],
    "concerns": [
      "Limited direct experience in AI strategy",
      "Not explicitly clear on cloud expertise",
      "Fragmented experience across multiple roles"
    ],
    "key_factors": [
      {
        "factor": "Diverse tech experience",
        "direction": "positive",
        "weight": "medium"
      },
      {
        "factor": "AI infrastructure experience",
        "direction": "positive",
        "weight": "medium"
      },
      {
        "factor": "Lack of direct AI strategy experience",
        "direction": "negative",
        "weight": "high"
      }
    ]
  },
  "usage": {
    "input_tokens": 2958,
    "output_tokens": 211
  }
}