{
  "strategy": "blind_instruction",
  "variant": "baseline",
  "model": "mistral-small",
  "vendor": "mistral",
  "tier": "cheap",
  "jd": "jd_senior_fullstack",
  "run": 9,
  "elapsed_ms": 2646,
  "timestamp": "2026-06-08T16:47:50.167Z",
  "response": {
    "score": 9,
    "recommend_interview": "yes",
    "justification": "Bogdan demonstrates extensive and diverse full-stack experience with strong alignment to the primary and secondary technologies required for the role. His work spans high-scale systems, AI agent infrastructure, and cross-language development, with measurable impact in previous roles. While his recent experience includes leadership roles (e.g., Staff Engineer), his technical depth and breadth in full-stack development justify a mid-senior level fit for this individual contributor role. Minor concerns include less direct experience with Nest.js and Vitest, though his adaptability and polyglot background mitigate this risk.",
    "strengths": [
      "10+ years of full-stack development with deep TypeScript and Node.js expertise",
      "Strong track record in high-performance systems (e.g., real-time data integration handling millions of requests/sec)",
      "Proven experience in AI agent infrastructure and developer tooling (MCP, code generators)"
    ],
    "concerns": [
      "Limited direct experience with Nest.js and Vitest, though TypeScript/Node.js experience is strong",
      "Recent role as Staff Engineer may indicate potential misalignment with mid-senior individual contributor expectations",
      "Diverse tech stack usage (e.g., Dlang, Swift) could dilute focus on core required technologies"
    ],
    "key_factors": [
      {
        "factor": "Full-stack TypeScript/Node.js experience",
        "direction": "positive",
        "weight": "high"
      },
      {
        "factor": "High-scale system architecture and performance optimization",
        "direction": "positive",
        "weight": "high"
      },
      {
        "factor": "AI agent infrastructure and modern tooling exposure",
        "direction": "positive",
        "weight": "medium"
      }
    ]
  },
  "usage": {
    "input_tokens": 2947,
    "output_tokens": 346
  }
}