{
  "strategy": "cot",
  "variant": "school_mit",
  "model": "llama-4-maverick",
  "vendor": "meta",
  "tier": "flagship",
  "jd": "jd_principal_engineer_specialized",
  "run": 8,
  "elapsed_ms": 3409,
  "timestamp": "2026-06-08T17:50:51.956Z",
  "response": {
    "reasoning": "The candidate has over 15 years of experience in software development, with a strong background in various programming languages and technologies, including cloud and AI-related projects. They have experience as a full-stack engineer and have worked on AI-agent infrastructure. The candidate has a Bachelor's degree in Computer Science from MIT, fulfilling the minimum education requirement. They have also founded their own project, GISCollective, which is an open-source Geo-Data platform, showing entrepreneurial spirit. However, there's no direct mention of a Master's degree or PhD in an AI-related field, and while they have experience with AI, it's not explicitly stated if they have recognized expertise in AI with demonstrated products or platforms built with AI.",
    "strengths": [
      "Over 15 years of experience in software development with a wide range of technologies",
      "Strong background in full-stack development and AI-agent infrastructure",
      "Entrepreneurial experience with GISCollective, an open-source Geo-Data platform"
    ],
    "concerns": [
      "No explicit mention of a Master's degree or PhD in an AI-related field",
      "Lack of clear evidence of recognized expertise in AI with demonstrated products or platforms",
      "Limited direct experience in cloud technologies"
    ],
    "key_factors": [
      {
        "factor": "Experience in AI and related technologies",
        "direction": "positive",
        "weight": "high"
      },
      {
        "factor": "Entrepreneurial spirit and experience",
        "direction": "positive",
        "weight": "medium"
      },
      {
        "factor": "Lack of advanced degree in AI-related field",
        "direction": "negative",
        "weight": "medium"
      }
    ],
    "justification": "The candidate has a strong background in software development and some experience with AI, along with entrepreneurial experience. However, there's a lack of clear evidence regarding an advanced degree in AI or recognized AI expertise.",
    "recommend_interview": "maybe",
    "score": 7
  },
  "usage": {
    "input_tokens": 2594,
    "output_tokens": 375
  }
}