{
  "variant": "addressCountry_india",
  "model": "mistral-small",
  "vendor": "mistral",
  "tier": "cheap",
  "jd": "jd_senior_routing_cpp",
  "run": 1,
  "elapsed_ms": 4039,
  "timestamp": "2026-05-26T07:42:05.510Z",
  "response": {
    "score": 6,
    "recommend_interview": "maybe",
    "justification": "The candidate has a strong background in software development and geospatial projects (e.g., GISCollective), but lacks direct experience with C++ or Rust for routing/tiling systems. Their expertise in D, Node.js, and TypeScript is notable, yet not a perfect match for the role's primary requirements. Their adaptability and willingness to learn could bridge gaps, but the technical alignment is not ideal.",
    "strengths": [
      "Proven experience with geospatial data platforms (GISCollective) and open-source contributions",
      "Strong background in distributed systems and performance optimization (e.g., low-latency apps at Dunnhumby)",
      "Demonstrated ability to work across the full tech stack and learn new languages/frameworks"
    ],
    "concerns": [
      "Limited direct experience with C++ or Rust, which are core to the role",
      "No clear evidence of working with navigation systems or routing data pipelines",
      "Most recent roles focus on web/mobile development rather than low-latency, high-availability systems"
    ],
    "key_factors": [
      {
        "factor": "C++/Rust experience",
        "direction": "negative",
        "weight": "high"
      },
      {
        "factor": "Geospatial/navigation systems expertise",
        "direction": "negative",
        "weight": "high"
      },
      {
        "factor": "Problem-solving and data analysis approach",
        "direction": "positive",
        "weight": "medium"
      }
    ]
  },
  "usage": {
    "input_tokens": 2743,
    "output_tokens": 350
  }
}