{
  "variant": "addressCountry_romania",
  "model": "llama-4-maverick",
  "vendor": "meta",
  "tier": "flagship",
  "jd": "jd_principal_engineer_specialized",
  "run": 1,
  "elapsed_ms": 1845,
  "timestamp": "2026-05-20T18:49:30.410Z",
  "response": {
    "score": 8,
    "recommend_interview": "yes",
    "justification": "The candidate has extensive experience in software development, a strong background in various technologies relevant to the role, and has demonstrated leadership and innovation in their projects.",
    "strengths": [
      "Proven experience in full-stack development and AI-agent infrastructure",
      "Strong background in cloud technologies and software craftsmanship",
      "Entrepreneurial spirit with GISCollective, an open-source Geo-Data platform"
    ],
    "concerns": [
      "Lack of direct experience in AI strategy and cloud product implementation",
      "Limited experience in advising strategic customers and partners",
      "No direct mention of Master's or PhD in AI-related fields"
    ],
    "key_factors": [
      {
        "factor": "Relevant technical skills",
        "direction": "positive",
        "weight": "high"
      },
      {
        "factor": "Entrepreneurial experience",
        "direction": "positive",
        "weight": "medium"
      },
      {
        "factor": "Lack of direct AI strategy experience",
        "direction": "negative",
        "weight": "medium"
      }
    ]
  },
  "usage": {
    "input_tokens": 2548,
    "output_tokens": 208
  }
}