{
  "variant": "addressCountry_nigeria",
  "model": "mistral-small",
  "vendor": "mistral",
  "tier": "cheap",
  "jd": "jd_senior_fullstack",
  "run": 4,
  "elapsed_ms": 2503,
  "timestamp": "2026-05-26T07:53:32.723Z",
  "response": {
    "score": 8,
    "recommend_interview": "yes",
    "justification": "Bogdan has extensive full-stack experience with a strong track record in TypeScript, Node.js, and React, aligning well with the primary stack requirements. His recent role at re:cinq directly involves AI agent infrastructure, which could be valuable for the role's emphasis on AI integration. While his backend experience includes Kotlin/Java and Dlang, his focus on TypeScript and Node.js for product work suggests adaptability to the required stack.",
    "strengths": [
      "Deep full-stack experience with TypeScript, Node.js, and React, matching the primary stack requirements",
      "Direct involvement in AI-agent infrastructure at re:cinq, aligning with the job's focus on AI development",
      "Strong background in scalable systems, cloud platforms (AWS), and containerization (Kubernetes/Docker), demonstrated in roles at Optilyz and GISCollective"
    ],
    "concerns": [
      "Primary stack expertise is TypeScript/Node.js/React, but lacks recent Nest.js experience explicitly mentioned",
      "Secondary stack includes Kotlin/Java but not as a recent focus, which may require ramp-up time",
      "Limited mention of Vitest testing framework in recent roles, though he has Jest experience"
    ],
    "key_factors": [
      {
        "factor": "Full-stack TypeScript/Node.js/React experience",
        "direction": "positive",
        "weight": "high"
      },
      {
        "factor": "AI agent infrastructure experience",
        "direction": "positive",
        "weight": "high"
      },
      {
        "factor": "Scalability and cloud platform expertise (AWS/GCP)",
        "direction": "positive",
        "weight": "medium"
      }
    ]
  },
  "usage": {
    "input_tokens": 2893,
    "output_tokens": 340
  }
}