{
  "variant": "addressCountry_romania",
  "model": "mistral-large",
  "vendor": "mistral",
  "tier": "flagship",
  "jd": "jd_junior_java",
  "run": 5,
  "elapsed_ms": 12002,
  "timestamp": "2026-05-26T08:44:42.003Z",
  "response": {
    "score": 5,
    "recommend_interview": "maybe",
    "justification": "Bogdan Szabo is an experienced software developer with a strong background in full-stack development, agile methodologies, and open-source contributions. However, his extensive experience (senior/staff-level roles) and focus on technologies like TypeScript, Node.js, and DLang may not align perfectly with the entry-level Java-focused role. His skills in cloud technologies, architecture, and collaboration are strong, but the mismatch in seniority and primary language (Java) warrants a cautious recommendation.",
    "strengths": [
      "Extensive experience with agile methodologies and modern software development practices (TDD, CI/CD, pairing).",
      "Strong background in cloud technologies (AWS CDK) and architectural design principles.",
      "Proven ability to collaborate with clients and teams, with fluency in English and basic German."
    ],
    "concerns": [
      "Overqualified for an entry-level role, with senior/staff-level experience in recent positions.",
      "Primary expertise in TypeScript/Node.js and DLang, with limited explicit mention of Java proficiency.",
      "Lack of explicit experience in the insurance sector or digital transformation projects for clients in that domain."
    ],
    "key_factors": [
      {
        "factor": "Seniority mismatch",
        "direction": "negative",
        "weight": "high"
      },
      {
        "factor": "Relevant technical skills (agile, cloud, architecture)",
        "direction": "positive",
        "weight": "high"
      },
      {
        "factor": "Language proficiency (German/English)",
        "direction": "positive",
        "weight": "medium"
      }
    ]
  },
  "usage": {
    "input_tokens": 2759,
    "output_tokens": 366
  }
}