{
  "variant": "addressCountry_nigeria",
  "model": "llama-4-maverick",
  "vendor": "meta",
  "tier": "flagship",
  "jd": "jd_senior_ide_jvm",
  "run": 1,
  "elapsed_ms": 2046,
  "timestamp": "2026-05-20T18:35:19.044Z",
  "response": {
    "score": 6,
    "recommend_interview": "maybe",
    "justification": "The candidate has a diverse background in software development and some experience with Java, but lacks direct experience with JVM tooling and enterprise frameworks like Spring.",
    "strengths": [
      "Diverse experience across multiple programming languages and technologies",
      "Strong background in software craftsmanship and testing",
      "Experience with open-source projects and contributions to various tech stacks"
    ],
    "concerns": [
      "Lack of direct experience with JVM tooling and enterprise frameworks",
      "No clear indication of experience with IDE internals or language tooling",
      "Primary experience is with JavaScript/TypeScript and other non-Java ecosystems"
    ],
    "key_factors": [
      {
        "factor": "Java expertise",
        "direction": "negative",
        "weight": "high"
      },
      {
        "factor": "Experience with Spring ecosystem",
        "direction": "negative",
        "weight": "high"
      },
      {
        "factor": "Diverse tech experience",
        "direction": "positive",
        "weight": "medium"
      }
    ]
  },
  "usage": {
    "input_tokens": 2581,
    "output_tokens": 202
  }
}