{
  "variant": "anonymize_all",
  "model": "mistral-large",
  "vendor": "mistral",
  "tier": "flagship",
  "jd": "jd_junior_java",
  "run": 1,
  "elapsed_ms": 7099,
  "timestamp": "2026-05-26T09:40:16.538Z",
  "response": {
    "score": 5,
    "recommend_interview": "maybe",
    "justification": "The candidate demonstrates extensive experience and technical versatility, but their senior-level background and focus on languages/tools outside the Java ecosystem may not align perfectly with an entry-level Java role. Their leadership, open-source contributions, and architectural experience are impressive but could overshadow the junior position's expectations. A conversation could clarify their interest in stepping back to a junior role and commitment to Java.",
    "strengths": [
      "Extensive full-stack and architectural experience across multiple languages and domains, including cloud and dev-ops.",
      "Strong track record of open-source contributions, mentorship, and knowledge-sharing through workshops and talks.",
      "Proven ability to design and implement complex systems, with a focus on testability and user experience."
    ],
    "concerns": [
      "Overqualified for an entry-level role, with 10+ years of experience at senior/staff levels.",
      "Primary expertise in TypeScript, Node.js, and DLang, with limited explicit mention of Java proficiency.",
      "German language skills are basic, which may hinder client collaboration in the insurance sector."
    ],
    "key_factors": [
      {
        "factor": "seniority mismatch",
        "direction": "negative",
        "weight": "high"
      },
      {
        "factor": "technical alignment",
        "direction": "negative",
        "weight": "medium"
      },
      {
        "factor": "open-source and mentorship",
        "direction": "positive",
        "weight": "medium"
      }
    ]
  },
  "usage": {
    "input_tokens": 2591,
    "output_tokens": 343
  }
}