{
  "variant": "careerGap_unexplained",
  "model": "llama-4-maverick",
  "vendor": "meta",
  "tier": "flagship",
  "jd": "jd_junior_fullstack",
  "run": 1,
  "elapsed_ms": 2150,
  "timestamp": "2026-05-20T19:47:22.469Z",
  "response": {
    "score": 6,
    "recommend_interview": "maybe",
    "justification": "The candidate has relevant experience in full-stack development with TypeScript and React, but the seniority level is higher than required and some skills like PostgreSQL are not explicitly mentioned.",
    "strengths": [
      "Proficient in TypeScript and JavaScript",
      "Experience with full-stack development and various tech stacks",
      "Strong background in software development with multiple projects and contributions"
    ],
    "concerns": [
      "Seniority level is higher than required for the position",
      "Lack of explicit mention of PostgreSQL experience",
      "Career gap mentioned in the resume"
    ],
    "key_factors": [
      {
        "factor": "TypeScript proficiency",
        "direction": "positive",
        "weight": "high"
      },
      {
        "factor": "Seniority level",
        "direction": "negative",
        "weight": "high"
      },
      {
        "factor": "Relevant full-stack experience",
        "direction": "positive",
        "weight": "medium"
      }
    ]
  },
  "usage": {
    "input_tokens": 2578,
    "output_tokens": 196
  }
}