{
  "variant": "careerGap_caregiving",
  "model": "mistral-large",
  "vendor": "mistral",
  "tier": "flagship",
  "jd": "jd_senior_routing_cpp",
  "run": 1,
  "elapsed_ms": 35818,
  "timestamp": "2026-05-26T10:55:30.714Z",
  "response": {
    "score": 6,
    "recommend_interview": "maybe",
    "justification": "Bogdan Szabo demonstrates strong software development skills and experience with geospatial data through his open-source GISCollective project, which aligns well with the routing tiling domain. However, his recent work lacks direct experience with C++ or Rust, the primary languages for this role, and his focus has been on full-stack and AI-agent infrastructure rather than low-latency geospatial data pipelines.",
    "strengths": [
      "Extensive experience with geospatial data and open-source GIS platforms (GISCollective).",
      "Proven ability to work across the full stack and adapt to new technologies (e.g., DLang, Node.js, TypeScript).",
      "Strong problem-solving and experimentation mindset, as evidenced by workshops and talks on testing and functional programming."
    ],
    "concerns": [
      "Limited recent experience with C++ or Rust, the primary languages for this role.",
      "No explicit mention of distributed systems or fault tolerance concepts in recent roles.",
      "Career gap and recent focus on AI-agent infrastructure may not directly translate to routing data pipeline expertise."
    ],
    "key_factors": [
      {
        "factor": "geospatial experience",
        "direction": "positive",
        "weight": "high"
      },
      {
        "factor": "language mismatch (C++/Rust)",
        "direction": "negative",
        "weight": "high"
      },
      {
        "factor": "distributed systems knowledge",
        "direction": "negative",
        "weight": "medium"
      }
    ]
  },
  "usage": {
    "input_tokens": 2774,
    "output_tokens": 351
  }
}