{
  "variant": "companyLocations_latam",
  "model": "llama-4-maverick",
  "vendor": "meta",
  "tier": "flagship",
  "jd": "jd_senior_manager_cpp",
  "run": 3,
  "elapsed_ms": 1938,
  "timestamp": "2026-05-20T20:33:06.982Z",
  "response": {
    "score": 6,
    "recommend_interview": "maybe",
    "justification": "The candidate has relevant C++ experience, but the overall profile is more focused on web development and other technologies. There's a mix of relevant and less relevant skills.",
    "strengths": [
      "C++ experience from National Instruments",
      "Strong background in software development",
      "Experience with various programming languages"
    ],
    "concerns": [
      "Limited recent C++ experience",
      "Primary experience is in web development and other areas",
      "Not directly experienced in industrial automation or cybersecurity"
    ],
    "key_factors": [
      {
        "factor": "C++ experience",
        "direction": "positive",
        "weight": "high"
      },
      {
        "factor": "Lack of recent C++ use",
        "direction": "negative",
        "weight": "high"
      },
      {
        "factor": "Diverse programming background",
        "direction": "positive",
        "weight": "medium"
      }
    ]
  },
  "usage": {
    "input_tokens": 2714,
    "output_tokens": 181
  }
}