{
  "variant": "companyNames_unknown-regional",
  "model": "mistral-large",
  "vendor": "mistral",
  "tier": "flagship",
  "jd": "jd_senior_routing_cpp",
  "run": 4,
  "elapsed_ms": 6289,
  "timestamp": "2026-05-26T15:37:22.805Z",
  "response": {
    "score": 6,
    "recommend_interview": "maybe",
    "justification": "Bogdan Szabo demonstrates strong full-stack and geospatial experience, particularly with his open-source Geo-Data platform and GISCollective project. However, his recent work lacks direct alignment with the core requirements of C++/Rust for routing tiling pipelines and distributed systems expertise. His problem-solving approach and willingness to learn are positive, but the role demands deeper specialization in navigation data pipelines and low-latency systems.",
    "strengths": [
      "Extensive geospatial experience with open-source projects (e.g., GISCollective, Northwind Labs platform).",
      "Proven ability to design and maintain scalable, event-driven data platforms (Node.js, Kubernetes).",
      "Strong problem-solving mindset with a focus on experimentation and data analysis (e.g., workshops, TDD)."
    ],
    "concerns": [
      "Limited recent experience with C++ or Rust, the primary languages for this role.",
      "No explicit experience with routing data pipelines or navigation systems in commercial environments.",
      "Most recent work (Acme Software, Pinepoint Systems) is full-stack/TypeScript-focused, diverging from the role's technical stack."
    ],
    "key_factors": [
      {
        "factor": "geospatial experience",
        "direction": "positive",
        "weight": "high"
      },
      {
        "factor": "C++/Rust expertise",
        "direction": "negative",
        "weight": "high"
      },
      {
        "factor": "distributed systems knowledge",
        "direction": "negative",
        "weight": "medium"
      }
    ]
  },
  "usage": {
    "input_tokens": 2740,
    "output_tokens": 362
  }
}