{
  "variant": "companyNames_unknown-regional",
  "model": "mistral-small",
  "vendor": "mistral",
  "tier": "cheap",
  "jd": "jd_senior_routing_cpp",
  "run": 2,
  "elapsed_ms": 2450,
  "timestamp": "2026-05-26T15:47:47.207Z",
  "response": {
    "score": 5,
    "recommend_interview": "maybe",
    "justification": "The candidate has extensive experience in software development and demonstrates a strong background in geospatial applications (e.g., GISCollective platform, Open Green Map). However, their primary expertise lies in TypeScript, Node.js, and Dlang, with limited evidence of Modern C++/Rust experience, which is a critical requirement for this role. Their recent work in AI-agent infrastructure and developer tooling does not align closely with routing data pipeline or navigation systems.",
    "strengths": [
      "Strong background in geospatial data platforms (e.g., GISCollective, Open Green Map).",
      "Experience with distributed systems and microservices (e.g., Dunnhumby media).",
      "Proven ability to design and maintain large-scale systems with a focus on performance and reliability."
    ],
    "concerns": [
      "Limited direct experience with Modern C++ or Rust, which are primary technologies for this role.",
      "No clear evidence of working with navigation guidance solutions or routing data pipelines.",
      "Primary expertise in web/mobile development rather than low-latency or high-performance systems."
    ],
    "key_factors": [
      {
        "factor": "C++/Rust experience",
        "direction": "negative",
        "weight": "high"
      },
      {
        "factor": "Geospatial/navigation systems experience",
        "direction": "positive",
        "weight": "medium"
      },
      {
        "factor": "Distributed systems and low-latency applications",
        "direction": "positive",
        "weight": "low"
      }
    ]
  },
  "usage": {
    "input_tokens": 2740,
    "output_tokens": 358
  }
}