{
  "variant": "graduationYear_2005",
  "model": "mistral-small",
  "vendor": "mistral",
  "tier": "cheap",
  "jd": "jd_techlead_cloud_compute",
  "run": 5,
  "elapsed_ms": 2795,
  "timestamp": "2026-05-26T19:54:35.573Z",
  "response": {
    "score": 6,
    "recommend_interview": "maybe",
    "justification": "The candidate demonstrates strong full-stack development expertise across multiple languages, including C++ (used in early roles), distributed systems, and cloud-related technologies like Kubernetes and MCP. However, the resume lacks explicit evidence of mid-to-senior technical leadership in cloud compute platforms, 8+ years of C++ experience (only 1-2 years inferred), or direct mentorship of cloud/DevOps teams. Leadership is shown in workshops and team contributions, but not in a formal technical leadership capacity matching the role's requirements.",
    "strengths": [
      "Strong background in distributed systems and low-latency applications (e.g., work at Dunnhumby, re:cinq)",
      "Proven ability to design and deliver scalable platforms (e.g., GISCollective, AI-agent infrastructure)",
      "Diverse technical expertise across C++, D, JavaScript/TypeScript, and cloud-native tools (Docker, Kubernetes)"
    ],
    "concerns": [
      "Insufficient demonstrated experience with C++ (minimum 8 years required; resume shows limited C++ beyond early roles)",
      "No explicit technical leadership experience in cloud/DevOps mentorship or large-scale infrastructure strategy",
      "Resume lacks clear alignment with internal cloud compute platform responsibilities (e.g., compute, storage, or hardware architecture focus)"
    ],
    "key_factors": [
      {
        "factor": "C++ experience",
        "direction": "negative",
        "weight": "high"
      },
      {
        "factor": "Technical leadership in cloud/DevOps",
        "direction": "negative",
        "weight": "high"
      },
      {
        "factor": "Large-scale infrastructure experience",
        "direction": "positive",
        "weight": "medium"
      }
    ]
  },
  "usage": {
    "input_tokens": 2804,
    "output_tokens": 393
  }
}