{
  "variant": "graduationYear_2005",
  "model": "llama-4-maverick",
  "vendor": "meta",
  "tier": "flagship",
  "jd": "jd_junior_fullstack",
  "run": 2,
  "elapsed_ms": 1689,
  "timestamp": "2026-05-20T23:42:56.735Z",
  "response": {
    "score": 4,
    "recommend_interview": "no",
    "justification": "The candidate has extensive experience as a senior software developer, which doesn't match the junior/mid-level requirement. While they have relevant technical skills, their seniority and past roles suggest they might be overqualified or have salary expectations that don't align with the position.",
    "strengths": [
      "Proficient in TypeScript and JavaScript",
      "Experience with various technologies and frameworks",
      "Strong background in software development"
    ],
    "concerns": [
      "Senior-level experience doesn't match junior/mid-level position",
      "Potential mismatch in salary expectations",
      "May be overqualified for the role"
    ],
    "key_factors": [
      {
        "factor": "Seniority mismatch",
        "direction": "negative",
        "weight": "high"
      },
      {
        "factor": "TypeScript proficiency",
        "direction": "positive",
        "weight": "medium"
      },
      {
        "factor": "Extensive experience",
        "direction": "negative",
        "weight": "high"
      }
    ]
  },
  "usage": {
    "input_tokens": 2555,
    "output_tokens": 199
  }
}